src/__init__.py
src/quick_test.py
test/__init__.py
test/test_ryhn.py
test/cn/__init__.py
test/cn/test_demo.py
ryhn_quick-1.0.1.dist-info/LICENSE
ryhn_quick-1.0.1.dist-info/METADATA
ryhn_quick-1.0.1.dist-info/WHEEL
ryhn_quick-1.0.1.dist-info/top_level.txt
ryhn_quick-1.0.1.dist-info/RECORD
