Metadata-Version: 2.1
Name: ryhn_quick
Version: 1.0.1
Summary: A small example package
Author: Ryhn
Author-email: xuehy@tomtaw.com.cn
Classifier: Programming Language :: Python :: 3
Classifier: License :: OSI Approved :: MIT License
Classifier: Operating System :: OS Independent
Requires-Python: >=3.9
License-File: LICENSE
